repo_sync_kitty/__about__.py
repo_sync_kitty/__init__.py
repo_sync_kitty/__main__.py
repo_sync_kitty/cli.py
repo_sync_kitty/commands/__init__.py
repo_sync_kitty/commands/add.py
repo_sync_kitty/commands/check.py
repo_sync_kitty/commands/enroll.py
repo_sync_kitty/commands/find_orphans.py
repo_sync_kitty/commands/fix_detached.py
repo_sync_kitty/commands/import_manifest.py
repo_sync_kitty/commands/init.py
repo_sync_kitty/commands/move.py
repo_sync_kitty/commands/open.py
repo_sync_kitty/commands/scan.py
repo_sync_kitty/commands/scrub.py
repo_sync_kitty/commands/status.py
repo_sync_kitty/commands/sync.py
repo_sync_kitty/config/__init__.py
repo_sync_kitty/config/loader.py
repo_sync_kitty/config/models.py
repo_sync_kitty/forge/__init__.py
repo_sync_kitty/forge/bitbucket.py
repo_sync_kitty/forge/github.py
repo_sync_kitty/forge/gitlab.py
repo_sync_kitty/git/__init__.py
repo_sync_kitty/git/operations.py
repo_sync_kitty/git/retry.py
repo_sync_kitty/git/safety.py
repo_sync_kitty/output/__init__.py
repo_sync_kitty/output/display.py
repo_sync_kitty-0.2.1.dist-info/METADATA
repo_sync_kitty-0.2.1.dist-info/WHEEL
repo_sync_kitty-0.2.1.dist-info/entry_points.txt
repo_sync_kitty-0.2.1.dist-info/RECORD
