Metadata-Version: 2.4
Name: repo-sync-kitty
Version: 0.2.1
Summary: Git repository synchronization tool for teams
Project-URL: Homepage, https://github.com/vladistan/repo-sync-kitty
Project-URL: Bug Tracker, https://github.com/vladistan/repo-sync-kitty/issues
Author-email: Vlad Korolev <vlad@v-lad.org>
License-Expression: MIT
Keywords: git,repository,sync,team
Classifier: Development Status :: 3 - Alpha
Classifier: Environment :: Console
Classifier: Intended Audience :: Developers
Classifier: License :: OSI Approved :: MIT License
Classifier: Operating System :: OS Independent
Classifier: Programming Language :: Python :: 3.13
Classifier: Topic :: Software Development :: Version Control :: Git
Requires-Python: >=3.13
Requires-Dist: gitpython>=3.1.0
Requires-Dist: httpx>=0.25.0
Requires-Dist: pydantic-settings>=2.0.0
Requires-Dist: rich>=13.0.0
Requires-Dist: shellingham>=1.5.0
Requires-Dist: typer>=0.9.0
Provides-Extra: dev
Requires-Dist: mypy>=1.0.0; extra == 'dev'
Requires-Dist: pytest-cov>=4.0.0; extra == 'dev'
Requires-Dist: pytest>=7.0.0; extra == 'dev'
Requires-Dist: ruff>=0.1.0; extra == 'dev'
Provides-Extra: sentry
Requires-Dist: sentry-sdk>=1.0.0; extra == 'sentry'
